dapi/__init__.py
dapi/dapi_client.py
dapi/dapi_constants.py
dapi/dapi_request.py
dapi/dapi_utils.py
dapi/version.py
dapi/products/__init__.py
dapi/products/auth.py
dapi/products/data.py
dapi/products/metadata.py
dapi/products/operation.py
dapi/products/payment.py
dapi_python-2.3.0.dist-info/LICENSE
dapi_python-2.3.0.dist-info/METADATA
dapi_python-2.3.0.dist-info/WHEEL
dapi_python-2.3.0.dist-info/top_level.txt
dapi_python-2.3.0.dist-info/RECORD
