Metadata-Version: 2.1
Name: dapi-python
Version: 2.3.0
Summary: Python Library for Dapi API
Home-page: https://github.com/dapi-co/dapi-python
Author: DAPI LTD
Author-email: dev@dapi.com
Classifier: Programming Language :: Python :: 3
Classifier: License :: OSI Approved :: Apache Software License
Classifier: Operating System :: OS Independent
Requires-Python: >=3.6
License-File: LICENSE
Requires-Dist: requests (>=2.7.0)
